odoo/addons/account_payment_base_oca/README.rst
odoo/addons/account_payment_base_oca/__init__.py
odoo/addons/account_payment_base_oca/__manifest__.py
odoo/addons/account_payment_base_oca/demo/demo.xml
odoo/addons/account_payment_base_oca/i18n/account_payment_base_oca.pot
odoo/addons/account_payment_base_oca/i18n/fr.po
odoo/addons/account_payment_base_oca/i18n/it.po
odoo/addons/account_payment_base_oca/models/__init__.py
odoo/addons/account_payment_base_oca/models/account_move.py
odoo/addons/account_payment_base_oca/models/account_payment_method.py
odoo/addons/account_payment_base_oca/models/account_payment_method_line.py
odoo/addons/account_payment_base_oca/models/res_bank.py
odoo/addons/account_payment_base_oca/models/res_partner.py
odoo/addons/account_payment_base_oca/models/res_partner_bank.py
odoo/addons/account_payment_base_oca/readme/CONTRIBUTORS.md
odoo/addons/account_payment_base_oca/readme/DESCRIPTION.md
odoo/addons/account_payment_base_oca/reports/__init__.py
odoo/addons/account_payment_base_oca/reports/account_invoice_report.py
odoo/addons/account_payment_base_oca/reports/account_invoice_report_view.xml
odoo/addons/account_payment_base_oca/security/ir_rule.xml
odoo/addons/account_payment_base_oca/static/description/icon.png
odoo/addons/account_payment_base_oca/static/description/index.html
odoo/addons/account_payment_base_oca/views/account_move.xml
odoo/addons/account_payment_base_oca/views/account_payment_method.xml
odoo/addons/account_payment_base_oca/views/account_payment_method_line.xml
odoo_addon_account_payment_base_oca-19.0.1.0.0.2.dist-info/METADATA
odoo_addon_account_payment_base_oca-19.0.1.0.0.2.dist-info/WHEEL
odoo_addon_account_payment_base_oca-19.0.1.0.0.2.dist-info/top_level.txt
odoo_addon_account_payment_base_oca-19.0.1.0.0.2.dist-info/RECORD
